{
  "app-id": "com.syzzle.singularity",
  "runtime": "org.freedesktop.Platform",
  "runtime-version": "25.08",
  "sdk": "org.freedesktop.Sdk",
  "command": "singularity-wrapper",
  "finish-args": [
    "--share=network",
    "--share=ipc",
    "--socket=fallback-x11",
    "--socket=wayland",
    "--device=dri",
    "--filesystem=home",
    "--filesystem=xdg-download",
    "--filesystem=xdg-documents",
    "--filesystem=xdg-desktop",
    "--env=EGL_PLATFORM=x11",
    "--env=ATK_ADAPTOR=dbus",
    "--env=WEBKIT_EXEC_PATH=/app/libexec/webkit2gtk-4.1",
    "--env=WEBKIT_DISABLE_COMPOSITING_MODE=1",
    "--talk-name=org.freedesktop.Notifications",
    "--talk-name=org.gtk.vfs.*",
    "--filesystem=xdg-run/gvfsd"
  ],
  "modules": [
    {
      "name": "webkit-helpers",
      "buildsystem": "simple",
      "build-commands": [
        "mkdir -p /app/libexec/webkit2gtk-4.1",
        "if [ -f /usr/libexec/webkit2gtk-4.1/WebKitNetworkProcess ]; then install -m755 /usr/libexec/webkit2gtk-4.1/WebKitNetworkProcess /app/libexec/webkit2gtk-4.1/; fi",
        "if [ -f /usr/libexec/webkit2gtk-4.1/WebKitWebProcess ]; then install -m755 /usr/libexec/webkit2gtk-4.1/WebKitWebProcess /app/libexec/webkit2gtk-4.1/; fi",
        "if [ -f /usr/lib/x86_64-linux-gnu/webkit2gtk-4.1/WebKitNetworkProcess ]; then install -m755 /usr/lib/x86_64-linux-gnu/webkit2gtk-4.1/WebKitNetworkProcess /app/libexec/webkit2gtk-4.1/; fi",
        "if [ -f /usr/lib/x86_64-linux-gnu/webkit2gtk-4.1/WebKitWebProcess ]; then install -m755 /usr/lib/x86_64-linux-gnu/webkit2gtk-4.1/WebKitWebProcess /app/libexec/webkit2gtk-4.1/; fi",
        "ls -la /app/libexec/webkit2gtk-4.1/ || echo 'No WebKit helpers found in system'"
      ]
    },
    {
      "name": "singularity",
      "buildsystem": "simple",
      "build-commands": [
        "mkdir -p /app/bin /app/lib /app/libexec /app/share/applications /app/share/icons/hicolor/128x128/apps",
        "install -m755 Singularity /app/bin/singularity",
        "echo 'Copying libraries excluding system libs...'",
        "find lib -name \"*.so*\" ! -name \"libc.so*\" ! -name \"libdl.so*\" ! -name \"libpthread.so*\" ! -name \"libm.so*\" ! -name \"librt.so*\" ! -name \"libresolv.so*\" ! -name \"libnss_*\" ! -name \"libutil.so*\" ! -name \"ld-linux*\" | xargs -I {} cp {} /app/lib/",
        "if [[ -d libexec ]]; then echo 'Copying additional libexec files...'; cp -r libexec/* /app/libexec/; fi",
        "install -m755 singularity-wrapper /app/bin/singularity-wrapper",
        "install -m644 singularity.desktop /app/share/applications/com.syzzle.singularity.desktop",
        "install -m644 singularity.png /app/share/icons/hicolor/128x128/apps/com.syzzle.singularity.png",
        "echo 'Final directory structure:'",
        "find /app -type f | head -20"
      ],
      "sources": [
        {
          "type": "dir",
          "path": "flatpak-source"
        }
      ]
    },
    {
      "name": "libcanberra",
      "buildsystem": "autotools",
      "config-opts": ["--enable-gtk3"],
      "sources": [
        {
          "type": "archive",
          "url": "https://0pointer.de/lennart/projects/libcanberra/libcanberra-0.30.tar.xz",
          "sha256": "c2b671e67e0c288a69fc33dc1b6f1b534d07882c2aceed37004bf48c601afa72"
        }
      ]
    },
    {
      "name": "util-linux",
      "buildsystem": "meson",
      "config-opts": [
        "-Dlastlog=false"
      ],
      "sources": [
        {
          "type": "archive",
          "url": "https://mirrors.edge.kernel.org/pub/linux/utils/util-linux/v2.40/util-linux-2.40.tar.xz",
          "sha256": "d57a626081f9ead02fa44c63a6af162ec19c58f53e993f206ab7c3a6641c2cd7"
        }
      ]
    }
  ]
}
